getout_of_text_3/__init__.py
getout_of_text_3/_config.py
getout_of_text_3/_version.py
getout_of_text_3/ai_agents.py
getout_of_text_3/corpus.py
getout_of_text_3/embeddinggemma.py
getout_of_text_3/legal_bert.py
getout_of_text_3/agents/bedrock/Wikimedia-Multilang.py
getout_of_text_3/agents/bedrock/__init__.py
getout_of_text_3/agents/bedrock/wikimedia_multilang.py
getout_of_text_3-0.4.10.dist-info/licenses/LICENSE.md
getout_of_text_3-0.4.10.dist-info/METADATA
getout_of_text_3-0.4.10.dist-info/WHEEL
getout_of_text_3-0.4.10.dist-info/top_level.txt
getout_of_text_3-0.4.10.dist-info/RECORD
