Metadata-Version: 2.4
Name: getout-of-text-3
Version: 0.4.10
Summary: A Python toolkit for working with legal corpora and English datasets.
Author-email: Etienne Jacquot <jacquot.etienne@gmail.com>
License: MIT
Project-URL: Homepage, https://github.com/atnjqt/getout_of_text3
Requires-Python: >=3.11
License-File: LICENSE.md
Requires-Dist: pandas>=1.0
Requires-Dist: numpy>=1.18
Requires-Dist: nltk>=3.8
Provides-Extra: embeddings
Requires-Dist: sentence-transformers>=3.0.0; extra == "embeddings"
Requires-Dist: torch>=2.0.0; extra == "embeddings"
Provides-Extra: legal
Requires-Dist: transformers>=4.40.0; extra == "legal"
Requires-Dist: matplotlib>=3.7.0; extra == "legal"
Requires-Dist: seaborn>=0.12.0; extra == "legal"
Requires-Dist: torch>=2.0.0; extra == "legal"
Provides-Extra: dev
Requires-Dist: pytest>=7.0; extra == "dev"
Requires-Dist: ruff>=0.5.0; extra == "dev"
Dynamic: license-file
